{"stats":{"minecraft:mined":{"minecraft:white_bed":4,"minecraft:farmland":1,"minecraft:cherry_log":190,"minecraft:grass_block":141,"minecraft:soul_soil":3,"minecraft:weeping_vines_plant":2,"minecraft:magma_block":1,"epic_knights_ores_and_alloys:silver_ore":43,"minecraft:iron_ore":83,"minecraft:cobbled_deepslate":2,"minecraft:fire":8,"minecraft:pumpkin":2,"minecraft:deepslate_lapis_ore":3,"argentinas_delight:basedearbolmate":1,"epic_knights_ores_and_alloys:tin_ore":8,"minecraft:spruce_slab":3,"minecraft:tripwire":1,"minecraft:brown_mushroom":5,"minecraft:smoker":2,"minecraft:soul_fire":31,"minecraft:amethyst_cluster":3,"farm_and_charm:wild_beetroots":10,"minecraft:torch":3,"farm_and_charm:wild_carrots":5,"minecraft:blast_furnace":9,"minecraft:poppy":5,"minecraft:chest":5,"minecraft:cobblestone":48,"minecraft:sugar_cane":37,"minecraft:oak_planks":11,"minecraft:wall_torch":1,"mca:cross_headstone":1,"minecraft:pink_petals":2,"minecraft:seagrass":1,"farm_and_charm:wild_onions":8,"minecraft:birch_log":27,"minecraft:pumpkin_stem":1,"minecraft:black_bed":4,"minecraft:grass":229,"minecraft:oak_log":16,"minecraft:dirt":38,"minecraft:netherrack":7,"minecraft:oak_leaves":15,"minecraft:deepslate":54,"minecraft:tuff":1,"minecraft:deepslate_diamond_ore":1,"minecraft:crimson_roots":10,"minecraft:spruce_leaves":47,"minecraft:large_fern":27,"minecraft:furnace":3,"minecraft:andesite":1,"minecraft:potatoes":125,"minecraft:deepslate_iron_ore":10,"minecraft:stripped_oak_log":8,"farm_and_charm:wild_oat":1,"farm_and_charm:wild_emmer":2,"minecraft:stone":205,"minecraft:bone_block":41,"minecraft:smithing_table":1,"minecraft:cherry_planks":72,"minecraft:soul_sand":5,"minecraft:dandelion":1,"minecraft:crafting_table":4,"farm_and_charm:wild_barley":2,"minecraft:tall_grass":82,"minecraft:copper_ore":8,"minecraft:lapis_ore":5,"minecraft:deepslate_gold_ore":20,"minecraft:diorite":34,"farm_and_charm:wild_lettuce":2,"minecraft:birch_planks":10,"minecraft:purple_bed":4,"minecraft:sweet_berry_bush":14,"minecraft:white_carpet":1,"minecraft:spruce_log":36,"minecraft:birch_leaves":4,"minecraft:yellow_bed":12,"minecraft:coal_ore":109,"minecraft:cherry_leaves":39,"minecraft:sunflower":3,"minecraft:gravel":38,"minecraft:cobweb":15,"farm_and_charm:wild_tomatoes":4,"minecraft:gold_ore":7,"farm_and_charm:wild_corn":1,"minecraft:fern":15},"minecraft:broken":{"minecraft:stone_pickaxe":2,"minecraft:stone_axe":1,"epic_knights_ores_and_alloys:silver_axe":1,"minecraft:wooden_pickaxe":2,"magistuarmory:tin_concavehalberd":1},"minecraft:killed":{"minecraft:spider":19,"minecraft:skeleton":31,"minecraft:illusioner":1,"minecraft:piglin":3,"minecraft:pig":1,"minecraft:iron_golem":3,"minecraft:creeper":13,"alexsmobs:crimson_mosquito":4,"minecraft:sheep":6,"minecraft:donkey":2,"minecraft:zombie":66,"alexsmobs:terrapin":1,"minecraft:stray":1,"alexsmobs:fly":1,"minecraft:cow":5,"mca:female_zombie_villager":1,"tameablebeasts:giant_grasshopper":1,"minecraft:drowned":2,"alexsmobs:bison":3,"alexsmobs:tusklin":2,"mimic:mimic":6,"tameablebeasts:tameable_chikote":1,"minecraft:hoglin":3,"alexsmobs:crocodile":1,"minecraft:enderman":3},"minecraft:picked_up":{"minecraft:iron_chestplate":1,"minecraft:smithing_table":3,"minecraft:potion":2,"minecraft:string":44,"minecraft:soul_soil":13,"minecraft:raw_copper":36,"minecraft:iron_leggings":2,"mimic:mimic_tongue":7,"minecraft:beetroot":57,"epic_knights_ores_and_alloys:raw_silver":42,"alexsmobs:blood_sac":6,"minecraft:cobbled_deepslate":56,"mca:book_death":1,"minecraft:spruce_planks":11,"epic_knights_ores_and_alloys:tin_axe":6,"minecraft:iron_boots":2,"minecraft:furnace":3,"minecraft:tipped_arrow":1,"minecraft:stick":93,"minecraft:torch":4,"antiquelegacy:iron_plate":4,"minecraft:porkchop":15,"minecraft:cherry_log":358,"minecraft:diorite":34,"epic_knights_ores_and_alloys:silver_pickaxe":6,"alexsmobs:centipede_leg":4,"minecraft:rotten_flesh":83,"magistuarmory:tin_concavehalberd":1,"epic_knights_ores_and_alloys:tin_hoe":3,"epic_knights_ores_and_alloys:silver_axe":2,"farm_and_charm:corn":8,"epic_knights_ores_and_alloys:tin_ingot":50,"minecraft:snowball":1,"minecraft:cobblestone":307,"minecraft:birch_log":27,"minecraft:pink_petals":41,"minecraft:magma_block":1,"magistuarmory:steel_ring":14,"minecraft:cooked_beef":14,"minecraft:cherry_planks":315,"minecraft:andesite":1,"minecraft:black_bed":5,"farm_and_charm:barley":8,"minecraft:smoker":2,"minecraft:potato":397,"alexsmobs:bison_fur":11,"minecraft:flint":2,"minecraft:lapis_lazuli":55,"minecraft:dirt":236,"minecraft:bone":61,"minecraft:bow":5,"minecraft:wheat_seeds":93,"minecraft:raw_gold":81,"magistuarmory:steel_heavywarhammer":4,"epic_knights_ores_and_alloys:raw_tin":46,"minecraft:oak_planks":30,"epic_knights_ores_and_alloys:tin_sword":2,"minecraft:cooked_porkchop":1,"magistuarmory:tin_ahlspiess":1,"minecraft:poisonous_potato":1,"minecraft:ink_sac":10,"minecraft:grass_block":2,"alexsmobs:animal_dictionary":11,"mimic:mimic_plate":5,"farm_and_charm:tomato_seeds":8,"farm_and_charm:tomato":8,"minecraft:diamond":5,"magistuarmory:leather_strip":40,"farm_and_charm:oat_seeds":1,"minecraft:golden_apple":3,"minecraft:emerald":14,"minecraft:bread":112,"alexsmobs:maggot":3,"minecraft:netherrack":3,"minecraft:crimson_roots":6,"minecraft:crafting_table":4,"minecraft:azure_bluet":1,"epic_knights_ores_and_alloys:steel_pickaxe":3,"minecraft:brown_mushroom":12,"friendsandfoes:totem_of_illusion":4,"minecraft:wooden_pickaxe":3,"minecraft:flint_and_steel":5,"minecraft:netherite_scrap":2,"minecraft:white_carpet":1,"minecraft:beef":50,"minecraft:poppy":9,"minecraft:spruce_slab":6,"minecraft:chest":5,"minecraft:sugar_cane":81,"antiquelegacy:weathered_eagle_standard":1,"minecraft:birch_sapling":4,"minecraft:egg":1,"minecraft:raw_iron":103,"minecraft:stone":28,"minecraft:carrot":55,"minecraft:arrow":53,"minecraft:weeping_vines":2,"magistuarmory:steel_ingot":114,"magistuarmory:steel_plate":12,"minecraft:shears":5,"minecraft:gold_ingot":44,"minecraft:mutton":15,"minecraft:white_wool":3,"minecraft:rail":2,"minecraft:bone_block":40,"minecraft:stripped_oak_log":8,"minecraft:glow_ink_sac":3,"minecraft:leather":22,"minecraft:birch_planks":11,"minecraft:filled_map":3,"minecraft:oak_log":12,"minecraft:yellow_bed":12,"minecraft:gunpowder":34,"mca:book_romance":1,"farm_and_charm:onion":108,"minecraft:cooked_mutton":3,"bonfires:ash_pile":28,"minecraft:apple":8,"minecraft:stone_bricks":3,"shy_guy:disturbing_photo":2,"epic_knights_ores_and_alloys:silver_shovel":4,"minecraft:iron_ingot":121,"minecraft:stone_pickaxe":10,"minecraft:cobweb":18,"minecraft:soul_sand":6,"minecraft:book":3,"farm_and_charm:lettuce":5,"minecraft:pumpkin":4,"minecraft:sweet_berries":37,"minecraft:dandelion":32,"minecraft:gravel":39,"minecraft:amethyst_shard":24,"minecraft:spruce_sapling":2,"minecraft:blast_furnace":9,"minecraft:white_bed":4,"minecraft:spruce_log":33,"minecraft:spider_eye":6,"magistuarmory:steel_chainmail":8,"minecraft:pumpkin_seeds":8,"minecraft:purple_bed":6,"minecraft:stone_axe":1,"minecraft:iron_helmet":2,"minecraft:cherry_sapling":65,"minecraft:gray_wool":1,"mca:book_infection":5,"argentinas_delight:cuernodetoro":10,"minecraft:black_wool":2,"magistuarmory:steel_nugget":11,"minecraft:coal":129,"minecraft:sunflower":4,"minecraft:ender_pearl":6},"minecraft:crafted":{"minecraft:black_dye":1,"magistuarmory:tin_kiteshield":1,"minecraft:oak_planks":80,"minecraft:smooth_stone":3,"minecraft:birch_boat":1,"magistuarmory:steel_heavywarhammer":1,"minecraft:stone":45,"minecraft:cooked_mutton":7,"minecraft:bow":1,"epic_knights_ores_and_alloys:steel_pickaxe":1,"epic_knights_ores_and_alloys:silver_shovel":1,"minecraft:chest":17,"magistuarmory:tin_concavehalberd":1,"packedup:basicbackpack":1,"magistuarmory:pole":4,"minecraft:black_wool":1,"minecraft:stone_bricks":40,"magistuarmory:steel_nugget":108,"magistuarmory:wood_kiteshield":1,"minecraft:cooked_porkchop":16,"minecraft:crafting_table":12,"minecraft:spruce_planks":132,"epic_knights_ores_and_alloys:tin_sword":1,"minecraft:wooden_pickaxe":2,"minecraft:baked_potato":52,"magistuarmory:steel_concavehalberd":1,"epic_knights_ores_and_alloys:tin_ingot":23,"magistuarmory:crusader_leggings":1,"minecraft:birch_planks":108,"minecraft:pumpkin_seeds":4,"epic_knights_ores_and_alloys:silver_ingot":15,"minecraft:stick":92,"minecraft:iron_ingot":92,"minecraft:iron_pickaxe":1,"magistuarmory:steel_chainmail":18,"minecraft:black_bed":1,"magistuarmory:tin_ahlspiess":1,"minecraft:shears":2,"magistuarmory:leather_strip":24,"minecraft:cherry_planks":316,"magistuarmory:knight_boots":2,"minecraft:furnace":7,"minecraft:blast_furnace":1,"epic_knights_ores_and_alloys:tin_axe":2,"minecraft:bone_meal":51,"minecraft:flint_and_steel":1,"magistuarmory:hilt":9,"antiquelegacy:iron_plate":2,"magistuarmory:knight_leggings":1,"magistuarmory:steel_ingot":70,"minecraft:stone_pickaxe":2,"magistuarmory:woolen_fabric":8,"magistuarmory:steel_ring":176,"epic_knights_ores_and_alloys:silver_pickaxe":2,"magistuarmory:steel_plate":14,"minecraft:cooked_beef":26,"epic_knights_ores_and_alloys:tin_pickaxe":1,"epic_knights_ores_and_alloys:silver_axe":2,"magistuarmory:platemail_chestplate":2,"magistuarmory:greathelm":2,"minecraft:bucket":1,"minecraft:stone_axe":1,"minecraft:air":0,"epic_knights_ores_and_alloys:tin_hoe":2,"magistuarmory:crusader_chestplate":1,"minecraft:torch":112},"minecraft:used":{"minecraft:beetroot":17,"minecraft:cherry_sapling":12,"minecraft:poppy":2,"minecraft:chest":21,"minecraft:rotten_flesh":38,"minecraft:soul_sand":4,"epic_knights_ores_and_alloys:steel_pickaxe":78,"minecraft:carrot":14,"farm_and_charm:lettuce":3,"minecraft:lava_bucket":9,"magistuarmory:steel_concavehalberd":33,"minecraft:grass_block":1,"minecraft:stone_bricks":43,"epic_knights_ores_and_alloys:tin_hoe":103,"minecraft:bow":15,"minecraft:sweet_berries":45,"minecraft:furnace":8,"minecraft:potato":181,"minecraft:stone_pickaxe":246,"minecraft:oak_planks":61,"minecraft:ender_pearl":1,"minecraft:wooden_pickaxe":106,"minecraft:sugar_cane":81,"epic_knights_ores_and_alloys:tin_axe":105,"minecraft:blast_furnace":9,"minecraft:black_bed":5,"minecraft:pumpkin_seeds":1,"minecraft:shears":9,"minecraft:bread":45,"minecraft:string":1,"minecraft:gravel":26,"magistuarmory:steel_heavywarhammer":119,"minecraft:smithing_table":1,"minecraft:bone_meal":51,"minecraft:cobweb":3,"epic_knights_ores_and_alloys:silver_axe":281,"epic_knights_ores_and_alloys:tin_pickaxe":131,"minecraft:flint_and_steel":1,"minecraft:torch":65,"minecraft:dirt":150,"farm_and_charm:onion":34,"minecraft:golden_carrot":2,"minecraft:beef":1,"minecraft:soul_soil":2,"magistuarmory:tin_kiteshield":26,"minecraft:cooked_beef":26,"minecraft:cobbled_deepslate":13,"farm_and_charm:tomato":5,"minecraft:cherry_log":110,"minecraft:cooked_mutton":7,"minecraft:water_bucket":12,"epic_knights_ores_and_alloys:tin_sword":36,"magistuarmory:tin_concavehalberd":153,"minecraft:birch_planks":53,"minecraft:baked_potato":49,"minecraft:birch_boat":1,"minecraft:cherry_planks":179,"epic_knights_ores_and_alloys:silver_pickaxe":118,"minecraft:crafting_table":15,"epic_knights_ores_and_alloys:silver_shovel":121,"minecraft:white_bed":4,"minecraft:smoker":1,"minecraft:sunflower":1,"minecraft:iron_pickaxe":143,"minecraft:spruce_sapling":1,"magistuarmory:tin_ahlspiess":54,"minecraft:stone_axe":112,"minecraft:cobblestone":140,"minecraft:purple_bed":5,"minecraft:cooked_porkchop":9,"minecraft:bucket":22,"minecraft:pumpkin_pie":1,"minecraft:yellow_bed":12,"alexsmobs:animal_dictionary":2},"minecraft:killed_by":{"shy_guy:shy_guy_rage":1,"minecraft:player":1},"minecraft:custom":{"minecraft:interact_with_crafting_table":126,"minecraft:open_barrel":3,"minecraft:leave_game":12,"minecraft:time_since_death":33197,"minecraft:sprint_one_cm":2233150,"minecraft:damage_blocked_by_shield":835,"minecraft:drop":163,"minecraft:talked_to_villager":28,"minecraft:play_time":589325,"minecraft:deaths":17,"minecraft:jump":10283,"minecraft:interact_with_brewingstand":1,"minecraft:walk_on_water_one_cm":37240,"minecraft:interact_with_furnace":76,"minecraft:sleep_in_bed":15,"minecraft:damage_dealt":25922,"minecraft:crouch_one_cm":10758,"minecraft:interact_with_smoker":12,"minecraft:mob_kills":191,"minecraft:climb_one_cm":1892,"minecraft:walk_one_cm":1319079,"minecraft:sneak_time":8986,"minecraft:walk_under_water_one_cm":8946,"minecraft:boat_one_cm":110054,"minecraft:interact_with_blast_furnace":84,"minecraft:total_world_time":589325,"minecraft:time_since_rest":3127,"minecraft:damage_taken":12131,"minecraft:swim_one_cm":40389,"minecraft:fly_one_cm":2210444,"minecraft:open_chest":156,"minecraft:fall_one_cm":272192},"minecraft:dropped":{"minecraft:soul_sand":2,"minecraft:glow_ink_sac":3,"magistuarmory:steel_heavywarhammer":1,"epic_knights_ores_and_alloys:silver_shovel":1,"minecraft:weeping_vines":2,"alexsmobs:bison_fur":2,"friendsandfoes:totem_of_illusion":1,"minecraft:flint":1,"minecraft:dirt":1,"minecraft:crimson_roots":4,"farm_and_charm:barley":8,"minecraft:white_wool":2,"minecraft:gold_ingot":13,"minecraft:bone":3,"magistuarmory:steel_ring":7,"antiquelegacy:weathered_eagle_standard":1,"minecraft:beetroot":3,"minecraft:rotten_flesh":14,"minecraft:oak_planks":7,"magistuarmory:leather_strip":8,"mimic:mimic_tongue":1,"magistuarmory:steel_chainmail":1,"farm_and_charm:tomato_seeds":1,"argentinas_delight:cuernodetoro":1,"mimic:mimic_plate":3,"minecraft:poppy":4,"alexsmobs:blood_sac":1,"mca:book_infection":2,"minecraft:iron_ingot":19,"minecraft:bread":1,"minecraft:cherry_log":2,"bonfires:ash_pile":4,"minecraft:apple":4,"magistuarmory:pole":1,"minecraft:stick":6,"antiquelegacy:iron_plate":2,"minecraft:gray_wool":1,"mca:book_romance":1,"magistuarmory:steel_ingot":12,"minecraft:pumpkin":1,"farm_and_charm:onion":1,"minecraft:string":6,"minecraft:pink_petals":3,"minecraft:furnace":1,"alexsmobs:maggot":3,"epic_knights_ores_and_alloys:tin_sword":1,"minecraft:soul_soil":2,"minecraft:raw_iron":1,"shy_guy:disturbing_photo":2,"magistuarmory:steel_nugget":2,"minecraft:pumpkin_seeds":5,"minecraft:flint_and_steel":1,"minecraft:filled_map":4,"minecraft:spider_eye":1,"minecraft:raw_gold":27}},"DataVersion":3465}